torch-stubs/torch/__config__.pyi
torch-stubs/torch/__future__.pyi
torch-stubs/torch/__init__.pyi
torch-stubs/torch/_appdirs.pyi
torch-stubs/torch/_classes.pyi
torch-stubs/torch/_compile.pyi
torch-stubs/torch/_custom_ops.pyi
torch-stubs/torch/_deploy.pyi
torch-stubs/torch/_environment.pyi
torch-stubs/torch/_guards.pyi
torch-stubs/torch/_jit_internal.pyi
torch-stubs/torch/_linalg_utils.pyi
torch-stubs/torch/_lobpcg.pyi
torch-stubs/torch/_lowrank.pyi
torch-stubs/torch/_meta_registrations.pyi
torch-stubs/torch/_namedtensor_internals.pyi
torch-stubs/torch/_ops.pyi
torch-stubs/torch/_python_dispatcher.pyi
torch-stubs/torch/_size_docs.pyi
torch-stubs/torch/_sources.pyi
torch-stubs/torch/_storage_docs.pyi
torch-stubs/torch/_streambase.pyi
torch-stubs/torch/_tensor.pyi
torch-stubs/torch/_tensor_docs.pyi
torch-stubs/torch/_tensor_str.pyi
torch-stubs/torch/_thread_safe_fork.pyi
torch-stubs/torch/_torch_docs.pyi
torch-stubs/torch/_utils.pyi
torch-stubs/torch/_utils_internal.pyi
torch-stubs/torch/_vmap_internals.pyi
torch-stubs/torch/_weights_only_unpickler.pyi
torch-stubs/torch/functional.pyi
torch-stubs/torch/hub.pyi
torch-stubs/torch/library.pyi
types_torch-0.1.1.dist-info/METADATA
types_torch-0.1.1.dist-info/WHEEL
types_torch-0.1.1.dist-info/top_level.txt
types_torch-0.1.1.dist-info/RECORD
